flik/__init__.py
flik/omdb.py
flik/reviewtools.py
flik/utils.py
flik-0.0.3.dist-info/LICENSE
flik-0.0.3.dist-info/METADATA
flik-0.0.3.dist-info/WHEEL
flik-0.0.3.dist-info/top_level.txt
flik-0.0.3.dist-info/RECORD
