Metadata-Version: 2.1
Name: flik
Version: 0.0.3
Summary: Flik, a Python Package for Film Buffs
Home-page: https://github.com/dariush-bahrami/flik
Author: Dariush Bahrami
Author-email: dariushbahrami1993@gmail.com
License: UNKNOWN
Project-URL: Bug Tracker, https://github.com/dariush-bahrami/flik/issues
Platform: UNKNOWN
Classifier: Programming Language :: Python :: 3
Classifier: License :: OSI Approved :: GNU General Public License v3 (GPLv3)
Classifier: Operating System :: OS Independent
Requires-Python: >=3.6
License-File: LICENSE
Requires-Dist: requests
Requires-Dist: bs4
Requires-Dist: fake-useragent
